LICENSE.nf
MANIFEST.in
README.nf
meta.json
setup.py
easypy/__init__.py
easypy/core.py
easypy/exceptions.py
easypy/helpers.py
easypy/tasks.py
easypy.egg-info/PKG-INFO
easypy.egg-info/SOURCES.txt
easypy.egg-info/dependency_links.txt
easypy.egg-info/entry_points.txt
easypy.egg-info/requires.txt
easypy.egg-info/top_level.txt